pdmt5/__init__.py
pdmt5/dataframe.py
pdmt5/mt5.py
pdmt5/trading.py
pdmt5/utils.py
pdmt5-0.2.2.dist-info/METADATA
pdmt5-0.2.2.dist-info/WHEEL
pdmt5-0.2.2.dist-info/licenses/LICENSE
pdmt5-0.2.2.dist-info/RECORD
