Metadata-Version: 2.4
Name: pdmt5
Version: 0.2.2
Summary: Pandas-based data handler for MetaTrader 5
Project-URL: Repository, https://github.com/dceoy/pdmt5.git
Author-email: dceoy <dceoy@users.noreply.github.com>
Maintainer-email: dceoy <dceoy@users.noreply.github.com>
License-Expression: MIT
License-File: LICENSE
Classifier: Development Status :: 4 - Beta
Classifier: Environment :: Console
Classifier: Intended Audience :: Financial and Insurance Industry
Classifier: License :: OSI Approved :: MIT License
Classifier: Operating System :: Microsoft :: Windows
Classifier: Programming Language :: Python
Classifier: Programming Language :: Python :: 3
Classifier: Topic :: Office/Business :: Financial :: Investment
Requires-Python: <3.14,>=3.11
Requires-Dist: metatrader5>=5.0.4424; sys_platform == 'win32'
Requires-Dist: pandas>=2.2.2
Requires-Dist: pydantic>=2.9.0
